[
    {
        "longitud": "-58.379677",
        "latitud": "-34.610694",
        "numero_registro": "20",
        "nombre": "PALACIO ALSINA",
        "calle": "ALSINA ",
        "numero": "934/44",
        "direccion_normalizada": "ALSINA  934",
        "numero_expediente": "34847653/18",
        "capacidad": "2140 personas",
        "clase": "\"C\"",
        "estado": "RENOVADO 2019",
        "disposicion": "23",
        "fecha_disp_inscripcion": "2005-03-10 00:00:00",
        "numero_dips": "9",
        "fecha_disp_re_inscripcion": "2019-01-23 00:00:00",
        "numero_disp_de_rechazo": "",
        "fecha_disposicion_de_rechazo": "",
        "numero_disposicion_de_recalculo_capacidad": "9",
        "fecha_disposicion_de_capacidad": "2017-02-02 00:00:00",
        "fecha_de_entrega_nueva_revalida": "2019-12-05",
        "vencimiento": "2020-03-03",
        "barrio": "",
        "comuna": "",
        "codigo_postal": "",
        "codigo_postal_argentino": ""
    },
    {
        "longitud": "",
        "latitud": "",
        "numero_registro": "38",
        "nombre": "CAIX",
        "calle": "R. OBLIGADO \nY SALGUERO",
        "numero": "sin nº",
        "direccion_normalizada": "R. OBLIGADO \nY SALGUERO ",
        "numero_expediente": "4960926/19",
        "capacidad": "1764 personas",
        "clase": "\"C\"",
        "estado": "RENOVADO 2019",
        "disposicion": "41",
        "fecha_disp_inscripcion": "2005-03-18 00:00:00",
        "numero_dips": "26",
        "fecha_disp_re_inscripcion": "2019-03-01 00:00:00",
        "numero_disp_de_rechazo": "",
        "fecha_disposicion_de_rechazo": "",
        "numero_disposicion_de_recalculo_capacidad": "134",
        "fecha_disposicion_de_capacidad": "2005-09-28 00:00:00",
        "fecha_de_entrega_nueva_revalida": "2019-11-14",
        "vencimiento": "2020-02-15",
        "barrio": "",
        "comuna": "",
        "codigo_postal": "",
        "codigo_postal_argentino": ""
    },
    {
        "longitud": "",
        "latitud": "",
        "numero_registro": "44",
        "nombre": "MANDARINE",
        "calle": "R. OBLIGADO \nY SARMIENTO",
        "numero": "sin nº",
        "direccion_normalizada": "R. OBLIGADO \nY SARMIENTO ",
        "numero_expediente": "2335460/19",
        "capacidad": "1613 personas",
        "clase": "\"C\"",
        "estado": "RENOVADO 2019",
        "disposicion": "47",
        "fecha_disp_inscripcion": "2005-03-23 00:00:00",
        "numero_dips": "8",
        "fecha_disp_re_inscripcion": "2019-01-22 00:00:00",
        "numero_disp_de_rechazo": "",
        "fecha_disposicion_de_rechazo": "",
        "numero_disposicion_de_recalculo_capacidad": "38",
        "fecha_disposicion_de_capacidad": "2009-03-23 00:00:00",
        "fecha_de_entrega_nueva_revalida": "2019-11-22",
        "vencimiento": "2020-02-21",
        "barrio": "",
        "comuna": "",
        "codigo_postal": "",
        "codigo_postal_argentino": ""
    },
    {
        "longitud": "",
        "latitud": "",
        "numero_registro": "76",
        "nombre": "DORSIA",
        "calle": "A.  MOREAU \nDE JUSTO",
        "numero": "2092",
        "direccion_normalizada": "A.  MOREAU \nDE JUSTO 2092",
        "numero_expediente": "24150733/19",
        "capacidad": "679 personas",
        "clase": "\"C\"",
        "estado": "RENOVADO 2019",
        "disposicion": "65",
        "fecha_disp_inscripcion": "2006-04-21 00:00:00",
        "numero_dips": "79",
        "fecha_disp_re_inscripcion": "2019-08-23 00:00:00",
        "numero_disp_de_rechazo": "",
        "fecha_disposicion_de_rechazo": "",
        "numero_disposicion_de_recalculo_capacidad": "83",
        "fecha_disposicion_de_capacidad": "2010-06-18 00:00:00",
        "fecha_de_entrega_nueva_revalida": "2019-08-06",
        "vencimiento": "2019-11-10",
        "barrio": "",
        "comuna": "Comuna 1",
        "codigo_postal": "1107",
        "codigo_postal_argentino": "C1107AFP"
    },
    {
        "longitud": "",
        "latitud": "",
        "numero_registro": "120",
        "nombre": "TERRAZAS \nDEL ESTE",
        "calle": "R. OBLIGADO \nY SARMIENTO",
        "numero": "",
        "direccion_normalizada": "R. OBLIGADO \nY SARMIENTO ",
        "numero_expediente": "36083286/2019",
        "capacidad": "3095 personas",
        "clase": "\"C\"",
        "estado": "RENOVADO 2019",
        "disposicion": "10",
        "fecha_disp_inscripcion": "2011-02-10 00:00:00",
        "numero_dips": "100",
        "fecha_disp_re_inscripcion": "2019-12-04 00:00:00",
        "numero_disp_de_rechazo": "",
        "fecha_disposicion_de_rechazo": " ",
        "numero_disposicion_de_recalculo_capacidad": "118",
        "fecha_disposicion_de_capacidad": "2016-12-27 00:00:00",
        "fecha_de_entrega_nueva_revalida": "",
        "vencimiento": "",
        "barrio": "",
        "comuna": "",
        "codigo_postal": "",
        "codigo_postal_argentino": ""
    },
    {
        "longitud": "-58.415350",
        "latitud": "-34.610722",
        "numero_registro": "48",
        "nombre": "EL FANTA NORTEÑO",
        "calle": "AV. RIVADAVIA ",
        "numero": "3469",
        "direccion_normalizada": "AV. RIVADAVIA  3469",
        "numero_expediente": "5318043/19",
        "capacidad": "1270 personas",
        "clase": "\"C\"",
        "estado": "RENOVADO 2019",
        "disposicion": "51",
        "fecha_disp_inscripcion": "2005-04-01 00:00:00",
        "numero_dips": "42",
        "fecha_disp_re_inscripcion": "2019-03-22 00:00:00",
        "numero_disp_de_rechazo": "10",
        "fecha_disposicion_de_rechazo": "2006-02-14 00:00:00",
        "numero_disposicion_de_recalculo_capacidad": "160",
        "fecha_disposicion_de_capacidad": "2005-12-22 00:00:00",
        "fecha_de_entrega_nueva_revalida": "2019-11-07",
        "vencimiento": "2019-12-22",
        "barrio": "Almagro",
        "comuna": "Comuna 5",
        "codigo_postal": "1203",
        "codigo_postal_argentino": "C1203AAG"
    },
    {
        "longitud": "-58.414942",
        "latitud": "-34.604021",
        "numero_registro": "52",
        "nombre": "EL PICAFLOR",
        "calle": "AV. CORRIENTES ",
        "numero": "3530",
        "direccion_normalizada": "AV. CORRIENTES  3530",
        "numero_expediente": "18874134/19",
        "capacidad": "550 personas",
        "clase": "\"C\"",
        "estado": "RENOVADO 2019",
        "disposicion": "56",
        "fecha_disp_inscripcion": "2005-05-04 00:00:00",
        "numero_dips": "65",
        "fecha_disp_re_inscripcion": "2019-07-17 00:00:00",
        "numero_disp_de_rechazo": "69",
        "fecha_disposicion_de_rechazo": "2006-05-04 00:00:00",
        "numero_disposicion_de_recalculo_capacidad": "65",
        "fecha_disposicion_de_capacidad": "2019-07-17 00:00:00",
        "fecha_de_entrega_nueva_revalida": "2019-10-29",
        "vencimiento": "2020-01-27",
        "barrio": "Almagro",
        "comuna": "Comuna 5",
        "codigo_postal": "1194",
        "codigo_postal_argentino": "C1194AAO"
    },
    {
        "longitud": "-58.423562",
        "latitud": "-34.598689",
        "numero_registro": "62",
        "nombre": "AMERIKA",
        "calle": "GASCON  ",
        "numero": "1036",
        "direccion_normalizada": "GASCON   1036",
        "numero_expediente": "17740746/19",
        "capacidad": "2450 personas",
        "clase": "\"C\"",
        "estado": "RENOVADO 2019",
        "disposicion": "84",
        "fecha_disp_inscripcion": "2005-07-14 00:00:00",
        "numero_dips": "76",
        "fecha_disp_re_inscripcion": "2019-08-21 00:00:00",
        "numero_disp_de_rechazo": "",
        "fecha_disposicion_de_rechazo": "",
        "numero_disposicion_de_recalculo_capacidad": "158",
        "fecha_disposicion_de_capacidad": "2012-12-20 00:00:00",
        "fecha_de_entrega_nueva_revalida": "2019-11-08",
        "vencimiento": "2020-02-10",
        "barrio": "Almagro",
        "comuna": "Comuna 5",
        "codigo_postal": "1181",
        "codigo_postal_argentino": "C1181ACT"
    },
    {
        "longitud": "-58.393750",
        "latitud": "-34.605027",
        "numero_registro": "1",
        "nombre": "CASTELBAMBA",
        "calle": "RIOBAMBA ",
        "numero": "345",
        "direccion_normalizada": "RIOBAMBA  345",
        "numero_expediente": "4978970/19",
        "capacidad": "428 personas",
        "clase": "\"C\"",
        "estado": "RENOVADO 2019",
        "disposicion": "1",
        "fecha_disp_inscripcion": "2005-02-24 00:00:00",
        "numero_dips": "18",
        "fecha_disp_re_inscripcion": "2019-02-20 00:00:00",
        "numero_disp_de_rechazo": "",
        "fecha_disposicion_de_rechazo": "",
        "numero_disposicion_de_recalculo_capacidad": "158",
        "fecha_disposicion_de_capacidad": "2005-12-12 00:00:00",
        "fecha_de_entrega_nueva_revalida": "2019-12-13",
        "vencimiento": "2020-01-13",
        "barrio": "Balvanera",
        "comuna": "Comuna 3",
        "codigo_postal": "1025",
        "codigo_postal_argentino": "C1025ABG"
    },
    {
        "longitud": "-58.408969",
        "latitud": "-34.609612",
        "numero_registro": "34",
        "nombre": "LATINO 11",
        "calle": "ECUADOR ",
        "numero": "60",
        "direccion_normalizada": "ECUADOR  60",
        "numero_expediente": "6446132/18",
        "capacidad": "1540 personas",
        "clase": "\"C\"",
        "estado": "RENOVADO 2019",
        "disposicion": "37",
        "fecha_disp_inscripcion": "2005-03-18 00:00:00",
        "numero_dips": "47",
        "fecha_disp_re_inscripcion": "2019-03-29 00:00:00",
        "numero_disp_de_rechazo": "",
        "fecha_disposicion_de_rechazo": "",
        "numero_disposicion_de_recalculo_capacidad": "34",
        "fecha_disposicion_de_capacidad": "2006-03-17 00:00:00",
        "fecha_de_entrega_nueva_revalida": "2019-12-18",
        "vencimiento": "2020-03-22",
        "barrio": "Balvanera",
        "comuna": "Comuna 3",
        "codigo_postal": "1214",
        "codigo_postal_argentino": "C1214ABB"
    },
    {
        "longitud": "-58.411863",
        "latitud": "-34.604651",
        "numero_registro": "67",
        "nombre": "THE FLOWER",
        "calle": "AGÜERO",
        "numero": "445",
        "direccion_normalizada": "AGÜERO 445",
        "numero_expediente": "23430067/19",
        "capacidad": "405 personas",
        "clase": "\"C\"",
        "estado": "RENOVADO 2019",
        "disposicion": "156",
        "fecha_disp_inscripcion": "2005-11-18 00:00:00",
        "numero_dips": "80",
        "fecha_disp_re_inscripcion": "2019-08-28 00:00:00",
        "numero_disp_de_rechazo": "",
        "fecha_disposicion_de_rechazo": "",
        "numero_disposicion_de_recalculo_capacidad": "156",
        "fecha_disposicion_de_capacidad": "2005-11-18 00:00:00",
        "fecha_de_entrega_nueva_revalida": "",
        "vencimiento": "",
        "barrio": "Balvanera",
        "comuna": "Comuna 3",
        "codigo_postal": "1171",
        "codigo_postal_argentino": "C1171ABE"
    },
    {
        "longitud": "-58.393721",
        "latitud": "-34.609365",
        "numero_registro": "68",
        "nombre": "LE CLICK",
        "calle": "AV. RIVADAVIA",
        "numero": "1908/12",
        "direccion_normalizada": "AV. RIVADAVIA 1908",
        "numero_expediente": "2489941/19",
        "capacidad": "990 personas",
        "clase": "\"C.C\"",
        "estado": "RENOVADO 2019",
        "disposicion": "159",
        "fecha_disp_inscripcion": "2005-12-14 00:00:00",
        "numero_dips": "5",
        "fecha_disp_re_inscripcion": "2019-01-18 00:00:00",
        "numero_disp_de_rechazo": "",
        "fecha_disposicion_de_rechazo": "",
        "numero_disposicion_de_recalculo_capacidad": "159",
        "fecha_disposicion_de_capacidad": "2005-12-14 00:00:00",
        "fecha_de_entrega_nueva_revalida": "2019-09-02",
        "vencimiento": "2019-10-13",
        "barrio": "Balvanera",
        "comuna": "Comuna 3",
        "codigo_postal": "1033",
        "codigo_postal_argentino": "C1033AAW"
    },
    {
        "longitud": "-58.412230",
        "latitud": "-34.602712",
        "numero_registro": "81",
        "nombre": "UNI CLUB",
        "calle": "GUARDIA VIEJA",
        "numero": "3360",
        "direccion_normalizada": "GUARDIA VIEJA 3360",
        "numero_expediente": "22273727/19",
        "capacidad": "630 personas",
        "clase": "\"C\"",
        "estado": "RENOVADO 2019",
        "disposicion": "101",
        "fecha_disp_inscripcion": "2006-08-11 00:00:00",
        "numero_dips": "69",
        "fecha_disp_re_inscripcion": "2019-07-26 00:00:00",
        "numero_disp_de_rechazo": "",
        "fecha_disposicion_de_rechazo": "",
        "numero_disposicion_de_recalculo_capacidad": "97",
        "fecha_disposicion_de_capacidad": "2007-11-16 00:00:00",
        "fecha_de_entrega_nueva_revalida": "2019-10-28",
        "vencimiento": "2020-01-27",
        "barrio": "Balvanera",
        "comuna": "Comuna 3",
        "codigo_postal": "1192",
        "codigo_postal_argentino": "C1192AAB"
    },
    {
        "longitud": "-58.409424",
        "latitud": "-34.598173",
        "numero_registro": "106",
        "nombre": "JANNOY",
        "calle": "AV. CORDOBA",
        "numero": "2988",
        "direccion_normalizada": "AV. CORDOBA 2988",
        "numero_expediente": "10658549/19",
        "capacidad": "448 personas",
        "clase": "C",
        "estado": "RENOVADO 2019",
        "disposicion": "54",
        "fecha_disp_inscripcion": "2009-04-30 00:00:00",
        "numero_dips": "51",
        "fecha_disp_re_inscripcion": "2019-04-24 00:00:00",
        "numero_disp_de_rechazo": "",
        "fecha_disposicion_de_rechazo": "",
        "numero_disposicion_de_recalculo_capacidad": "54",
        "fecha_disposicion_de_capacidad": "2009-04-30 00:00:00",
        "fecha_de_entrega_nueva_revalida": "2019-11-28",
        "vencimiento": "2020-02-17",
        "barrio": "Balvanera",
        "comuna": "Comuna 3",
        "codigo_postal": "1187",
        "codigo_postal_argentino": "C1187AAQ"
    }
]